{
  "name": "sweep-msb-scurrius-rigour-offtask",
  "source": "gen-parity-sweep.ts: Magic shortbow + rune arrows (rapid) vs scurrius [rigour-offtask] (weirdgloop@5e313c1)",
  "exercises": [
    "PlayerVsNpcCalc.dps"
  ],
  "inputs": {
    "player": {
      "skills": {
        "atk": 99,
        "str": 99,
        "def": 99,
        "hp": 99,
        "ranged": 99,
        "magic": 99,
        "prayer": 99,
        "mining": 99,
        "herblore": 99
      },
      "prayers": [
        "RIGOUR"
      ],
      "style": {
        "name": "Rapid",
        "type": "ranged",
        "stance": "Rapid"
      },
      "equipment": {
        "head": 27235,
        "cape": 28951,
        "neck": 19547,
        "body": 27238,
        "legs": 27241,
        "hands": 26235,
        "feet": 13237,
        "ring": 28310,
        "weapon": 861,
        "ammo": 892
      },
      "potions": [
        "RANGING"
      ],
      "buffs": {
        "onSlayerTask": false
      }
    },
    "monster": {
      "id": 7221,
      "version": "Group"
    }
  },
  "expected": {
    "maxAttackRoll": 42316,
    "npcDefRoll": 9156,
    "accuracy": 0.8917928964718671,
    "maxHit": 30,
    "dps": 7.4475894221485675,
    "ttk": 21.435899053056417
  },
  "weirdgloopCommit": "5e313c1b6cfba51d11a98c612243570a84772f44"
}
